[
    {
        "events": [
            {
                "article_title": "Gate.io Bi-Weekly Report (August 1-15, 2024)",
                "article_link": "https://www.gate.io/announcements/article/38636",
                "publish_datetime": "2024-08-17 02:28:45 UTC",
                "exchange_name": "Gate.io",
                "start_datetime": "2024-08-17 02:28:45 UTC",
                "end_datetime": "2024-08-17 02:28:45 UTC",
                "event_summary": "Gate.io listed 14 new projects and 17 Startup projects with airdrop value of $810,000. Held 9 trading competitions with $105,000 prize pool. Launched 18 financial products with up to 200% APR.",
                "event_type": [
                    "Report"
                ],
                "user_action_required": "",
                "separate_event_link": "",
                "tokens": [],
                "trading_pairs": [],
                "markets": [],
                "quantifiable_changes": [
                    "14 new projects listed",
                    "17 Startup projects listed",
                    "$810,000 total airdrop value",
                    "9 trading competitions",
                    "$105,000 total prize pool",
                    "18 financial products launched",
                    "APR up to 200%"
                ]
            }
        ]
    }
]