[
    {
        "type": "object",
        "properties": {
            "events": {
                "type": "array",
                "items": {
                    "type": "object",
                    "properties": {
                        "article_title": {
                            "type": "string"
                        },
                        "article_link": {
                            "type": "string"
                        },
                        "publish_datetime": {
                            "type": "string"
                        },
                        "exchange_name": {
                            "type": "string"
                        },
                        "start_datetime": {
                            "type": "string"
                        },
                        "end_datetime": {
                            "type": "string"
                        },
                        "event_summary": {
                            "type": "string"
                        },
                        "event_type": {
                            "type": "array",
                            "items": {
                                "type": "string"
                            }
                        },
                        "user_action_required": {
                            "type": "string"
                        },
                        "separate_event_link": {
                            "type": "string"
                        },
                        "tokens": {
                            "type": "array",
                            "items": {
                                "type": "string"
                            }
                        },
                        "trading_pairs": {
                            "type": "array",
                            "items": {
                                "type": "string"
                            }
                        },
                        "markets": {
                            "type": "array",
                            "items": {
                                "type": "string"
                            }
                        },
                        "quantifiable_changes": {
                            "type": "array",
                            "items": {
                                "type": "string"
                            }
                        }
                    }
                }
            }
        },
        "events": [
            {
                "article_title": "Gate.io Bi-Weekly Report (September 16-30, 2024)",
                "article_link": "https://www.gate.io/announcements/article/39677",
                "publish_datetime": "2024-10-02 16:11:44 UTC",
                "exchange_name": "Gate.io",
                "start_datetime": "2024-10-02 16:11:44 UTC",
                "end_datetime": "2024-10-02 16:11:44 UTC",
                "event_summary": "Gate.io bi-weekly report covering events from September 16 to 30, 2024, including new token listings, trading competitions, and financial products.",
                "event_type": [
                    "Report"
                ],
                "user_action_required": "",
                "separate_event_link": "https://www.gate.io/articlelist/ann",
                "tokens": [],
                "trading_pairs": [],
                "markets": [],
                "quantifiable_changes": []
            },
            {
                "article_title": "Gate.io Bi-Weekly Report (September 16-30, 2024)",
                "article_link": "https://www.gate.io/announcements/article/39677",
                "publish_datetime": "2024-10-02 16:11:44 UTC",
                "exchange_name": "Gate.io",
                "start_datetime": "2024-10-02 16:11:44 UTC",
                "end_datetime": "2024-10-02 16:11:44 UTC",
                "event_summary": "Gate.io listed 28 new projects and 34 Startup projects with a total airdrop value of $1,228,000 from September 16 to 30, 2024.",
                "event_type": [
                    "Listing",
                    "Airdrop"
                ],
                "user_action_required": "",
                "separate_event_link": "https://www.gate.io/startup",
                "tokens": [],
                "trading_pairs": [],
                "markets": [
                    "Launchpad/IEO"
                ],
                "quantifiable_changes": []
            },
            {
                "article_title": "Gate.io Bi-Weekly Report (September 16-30, 2024)",
                "article_link": "https://www.gate.io/announcements/article/39677",
                "publish_datetime": "2024-10-02 16:11:44 UTC",
                "exchange_name": "Gate.io",
                "start_datetime": "2024-10-02 16:11:44 UTC",
                "end_datetime": "2024-10-02 16:11:44 UTC",
                "event_summary": "Gate.io held 13 trading competitions with a total prize pool of $215,000 from September 16 to 30, 2024.",
                "event_type": [
                    "Trading_Competition"
                ],
                "user_action_required": "",
                "separate_event_link": "https://www.gate.io/competition/center/all/1",
                "tokens": [],
                "trading_pairs": [],
                "markets": [],
                "quantifiable_changes": []
            },
            {
                "article_title": "Gate.io Bi-Weekly Report (September 16-30, 2024)",
                "article_link": "https://www.gate.io/announcements/article/39677",
                "publish_datetime": "2024-10-02 16:11:44 UTC",
                "exchange_name": "Gate.io",
                "start_datetime": "2024-10-02 16:11:44 UTC",
                "end_datetime": "2024-10-02 16:11:44 UTC",
                "event_summary": "Gate.io launched 15 financial products in Hodl and Earn with an APR of up to 200% from September 16 to 30, 2024.",
                "event_type": [
                    "Product_Offering"
                ],
                "user_action_required": "",
                "separate_event_link": "https://www.gate.io/hodl",
                "tokens": [],
                "trading_pairs": [],
                "markets": [
                    "Earning"
                ],
                "quantifiable_changes": []
            },
            {
                "article_title": "Gate.io Bi-Weekly Report (September 16-30, 2024)",
                "article_link": "https://www.gate.io/announcements/article/39677",
                "publish_datetime": "2024-10-02 16:11:44 UTC",
                "exchange_name": "Gate.io",
                "start_datetime": "2024-10-02 16:11:44 UTC",
                "end_datetime": "2024-10-02 16:11:44 UTC",
                "event_summary": "Gate.io held various activities including Web3 Startup, Simple Earn, and Double Earning Monday from September 16 to 30, 2024.",
                "event_type": [
                    "Product_Offering",
                    "Learning_and_Education"
                ],
                "user_action_required": "",
                "separate_event_link": "https://www.gate.io/web3/startup",
                "tokens": [],
                "trading_pairs": [],
                "markets": [],
                "quantifiable_changes": []
            }
        ]
    }
]